MANIFEST.in
README.md
requirements.txt
setup.py
fuzzy_swagger/__init__.py
fuzzy_swagger/__main__.py
fuzzy_swagger/blns.txt
fuzzy_swagger/body_to_json.py
fuzzy_swagger/fuzz_generator.py
fuzzy_swagger/fuzzy_swagger.py
fuzzy_swagger/logger.py
fuzzy_swagger/orchestra.py
fuzzy_swagger/request_factory.py
fuzzy_swagger/swagger_doc.py
fuzzy_swagger.egg-info/PKG-INFO
fuzzy_swagger.egg-info/SOURCES.txt
fuzzy_swagger.egg-info/dependency_links.txt
fuzzy_swagger.egg-info/entry_points.txt
fuzzy_swagger.egg-info/requires.txt
fuzzy_swagger.egg-info/top_level.txt