Metadata-Version: 1.1
Name: fuzzy-swagger
Version: 0.1.9
Summary: Generates and run API fuzz tests against endpoints defined in swagger document.
Home-page: https://github.com/namuan/fuzzy-swagger
Author: Nauman Leghari
Author-email: nauman@docker-files.com
License: MIT
Keywords: swagger,apis,fuzz,testing
Platform: UNKNOWN
Classifier: Intended Audience :: Developers
Classifier: Natural Language :: English
Classifier: License :: OSI Approved :: MIT License
Classifier: Programming Language :: Python
Classifier: Programming Language :: Python :: 2.7
Classifier: Programming Language :: Python :: 3
Classifier: Programming Language :: Python :: 3.6
